hd_logging/SizeAndTimeLoggingHandler.py
hd_logging/__init__.py
hd_logging/env_loader.py
hd_logging/env_print.py
hd_logging/logger.py
hd_logging/otlp_formatter.py
hd_logging/py.typed
hd_logging-1.0.4.dist-info/WHEEL
hd_logging-1.0.4.dist-info/METADATA
hd_logging-1.0.4.dist-info/RECORD
