Metadata-Version: 2.3
Name: hd-logging
Version: 1.0.4
Summary: A comprehensive logging library with OpenTelemetry support, environment variable handling, and advanced log rotation
Keywords: logging,opentelemetry,environment,rotation
Author: Hackerdogs.ai
Author-email: Hackerdogs.ai <support@hackerdogs.ai>
License: Apache-2.0
Classifier: Development Status :: 4 - Beta
Classifier: Intended Audience :: Developers
Classifier: License :: OSI Approved :: Apache Software License
Classifier: Programming Language :: Python :: 3
Classifier: Programming Language :: Python :: 3.8
Classifier: Programming Language :: Python :: 3.9
Classifier: Programming Language :: Python :: 3.10
Classifier: Programming Language :: Python :: 3.11
Classifier: Programming Language :: Python :: 3.12
Classifier: Programming Language :: Python :: 3.13
Requires-Dist: colorlog>=6.9.0
Requires-Dist: python-dotenv>=1.0.0
Requires-Dist: python-ulid>=1.1.0
Requires-Dist: typing-extensions>=4.13.2
Requires-Dist: pytest>=7.0.0 ; extra == 'dev'
Requires-Dist: black>=23.0.0 ; extra == 'dev'
Requires-Dist: flake8>=6.0.0 ; extra == 'dev'
Requires-Dist: mypy>=1.0.0 ; extra == 'dev'
Requires-Python: >=3.8.1
Project-URL: Homepage, https://github.com/tejaswiredkar/hd-logging
Project-URL: Issues, https://github.com/tejaswiredkar/hd-logging/issues
Project-URL: Repository, https://github.com/tejaswiredkar/hd-logging
Provides-Extra: dev
